{
  "KERNCO-16CAP-00000-000O1": {
    "lat": 35.370619,
    "lng": -119.158179
  },
  "KERNCO-16CAP-00000-000MT": {
    "lat": 35.15587,
    "lng": -119.464286
  },
  "KERNCO-16CAP-00000-000KR": {
    "lat": 35.3755519,
    "lng": -118.9240568
  },
  "KERNCO-16CAP-00000-000LX": {
    "lat": 35.379515,
    "lng": -118.932802
  },
  "KERNCO-16CAP-00000-000KP": {
    "lat": 35.369312,
    "lng": -118.940078
  },
  "KERNCO-16CAP-00000-000M4": {
    "lat": 35.358005,
    "lng": -118.940584
  },
  "KERNCO-16CAP-00000-000N0": {
    "lat": 35.00401,
    "lng": -117.698888
  },
  "KERNCO-16CAP-00000-000KS": {
    "lat": 35.43551,
    "lng": -119.022179
  },
  "KERNCO-16CAP-00000-000N2": {
    "lat": 35.256301,
    "lng": -118.92084
  },
  "KERNCO-16CAP-00000-000O9": {
    "lat": 35.378666,
    "lng": -119.131318
  }
}
